easy_gui_prompt/__init__.py
easy_gui_prompt/easy_gui_prompt.py
easy_gui_prompt-2024.5.28.dist-info/LICENSE.txt
easy_gui_prompt-2024.5.28.dist-info/METADATA
easy_gui_prompt-2024.5.28.dist-info/WHEEL
easy_gui_prompt-2024.5.28.dist-info/RECORD
