Metadata-Version: 2.1
Name: easy_gui_prompt
Version: 2024.5.28
Summary: Simplify the creation of GUI elements in the terminal
Home-page: https://github.com/HenriquesLab/easy-gui-prompt
License: MIT
Author: Ricardo Henriques
Author-email: ricardo@henriqueslab.org
Requires-Python: >=3.10,<4.0
Classifier: License :: OSI Approved :: MIT License
Classifier: Programming Language :: Python :: 3
Classifier: Programming Language :: Python :: 3.10
Classifier: Programming Language :: Python :: 3.11
Classifier: Programming Language :: Python :: 3.12
Requires-Dist: prompt-toolkit (>=3.0.43,<4.0.0)
Requires-Dist: pyyaml (>=6.0.1,<7.0.0)
Requires-Dist: toml (>=0.10.2,<0.11.0)
Project-URL: Repository, https://github.com/HenriquesLab/easy-gui-prompt
